st2334_helper/__init__.py
st2334_helper/confidence_intervals.py
st2334_helper/general.py
st2334_helper/hypotheses_tests.py
ST2334_Helper-1.0.0.dist-info/LICENSE
ST2334_Helper-1.0.0.dist-info/METADATA
ST2334_Helper-1.0.0.dist-info/WHEEL
ST2334_Helper-1.0.0.dist-info/top_level.txt
ST2334_Helper-1.0.0.dist-info/RECORD
