Metadata-Version: 2.1
Name: ST2334-Helper
Version: 1.0.0
Summary: A computational tool for NUS module ST2334
Home-page: https://github.com/prit3010/ST2334-Helper
Author: Prittam Ravi & Kevin Chang Jon Kit
Author-email: kevinchangjk@gmail.com
License: UNKNOWN
Project-URL: Bug Tracker, https://github.com/prit3010/ST2334-Helper/issues
Keywords: python3,statistics
Platform: UNKNOWN
Classifier: Programming Language :: Python :: 3
Classifier: License :: OSI Approved :: MIT License
Classifier: Operating System :: OS Independent
Requires-Python: >=3.9
License-File: LICENSE
Requires-Dist: scipy (>=1.8.0)
